sexy_fun/__init__.py
sexy_fun-0.2.dist-info/METADATA
sexy_fun-0.2.dist-info/WHEEL
sexy_fun-0.2.dist-info/top_level.txt
sexy_fun-0.2.dist-info/RECORD
