Metadata-Version: 2.1
Name: sexy-fun
Version: 0.2
Summary: my usefull (maybe)sexy functions
Home-page: http://github.com/Greezye625/Sexy_Fun
Author: Greezye
Author-email: greezye625@gmail.com
License: None
Platform: UNKNOWN
Requires-Dist: pyautogui
